GoJianyiJiaocheng/README.md
GoJianyiJiaocheng/__init__.py
GoJianyiJiaocheng/__main__.py
GoJianyiJiaocheng/file.epub
GoJianyiJiaocheng/index.html
GoJianyiJiaocheng/css/__init__.py
GoJianyiJiaocheng/css/annotations.css
GoJianyiJiaocheng/css/main.css
GoJianyiJiaocheng/css/normalize.css
GoJianyiJiaocheng/css/popup.css
GoJianyiJiaocheng/font/__init__.py
GoJianyiJiaocheng/font/fontello.eot
GoJianyiJiaocheng/font/fontello.svg
GoJianyiJiaocheng/font/fontello.ttf
GoJianyiJiaocheng/font/fontello.woff
GoJianyiJiaocheng/img/__init__.py
GoJianyiJiaocheng/img/annotator-glyph-sprite.png
GoJianyiJiaocheng/img/annotator-icon-sprite.png
GoJianyiJiaocheng/img/apple-touch-icon.png
GoJianyiJiaocheng/img/cancelfullscreen.png
GoJianyiJiaocheng/img/close.png
GoJianyiJiaocheng/img/fullscreen.png
GoJianyiJiaocheng/img/loader.gif
GoJianyiJiaocheng/img/menu-icon.png
GoJianyiJiaocheng/img/save.png
GoJianyiJiaocheng/img/saved.png
GoJianyiJiaocheng/img/settings-s.png
GoJianyiJiaocheng/img/settings.png
GoJianyiJiaocheng/img/star.png
GoJianyiJiaocheng/js/__init__.py
GoJianyiJiaocheng/js/epub.js
GoJianyiJiaocheng/js/epub.min.js
GoJianyiJiaocheng/js/epub.min.map
GoJianyiJiaocheng/js/hooks.min.js
GoJianyiJiaocheng/js/hooks.min.map
GoJianyiJiaocheng/js/reader.js
GoJianyiJiaocheng/js/reader.js.map
GoJianyiJiaocheng/js/reader.min.js
GoJianyiJiaocheng/js/reader.min.map
GoJianyiJiaocheng/js/hooks/__init__.py
GoJianyiJiaocheng/js/hooks/extensions/__init__.py
GoJianyiJiaocheng/js/hooks/extensions/highlight.js
GoJianyiJiaocheng/js/libs/__init__.py
GoJianyiJiaocheng/js/libs/jquery.min.js
GoJianyiJiaocheng/js/libs/localforage.min.js
GoJianyiJiaocheng/js/libs/screenfull.js
GoJianyiJiaocheng/js/libs/screenfull.min.js
GoJianyiJiaocheng/js/libs/zip.min.js
GoJianyiJiaocheng/js/plugins/__init__.py
GoJianyiJiaocheng/js/plugins/hypothesis.js
GoJianyiJiaocheng/js/plugins/search.js
go_jianyi_jiaocheng-2024.3.2.0.dist-info/METADATA
go_jianyi_jiaocheng-2024.3.2.0.dist-info/WHEEL
go_jianyi_jiaocheng-2024.3.2.0.dist-info/entry_points.txt
go_jianyi_jiaocheng-2024.3.2.0.dist-info/top_level.txt
go_jianyi_jiaocheng-2024.3.2.0.dist-info/RECORD
